{
	"format_version": "1.8.0",
	"animations": {
		"idle": {
			"loop": true,
			"animation_length": 2,
			"bones": {
				"bone5": {
					"rotation": {
						"0.0": {
							"vector": [0, 0, 0]
						},
						"1.25": {
							"vector": [5, 0, -6],
							"easing": "easeInOutSine"
						},
						"2.0": {
							"vector": [0, 0, 0],
							"easing": "easeInOutSine"
						}
					},
					"position": {
						"0.0": {
							"vector": [0, 0, 0]
						},
						"2.0": {
							"vector": [0, 0, 0]
						}
					}
				},
				"UPERBODY": {
					"rotation": {
						"0.0": {
							"vector": [0, 0, 0]
						},
						"1.0": {
							"vector": [3, 0, 0],
							"easing": "easeInOutSine"
						},
						"2.0": {
							"vector": [0, 0, 0],
							"easing": "easeInOutSine"
						}
					},
					"position": {
						"0.0": {
							"vector": [0, 0, 0]
						},
						"2.0": {
							"vector": [0, 0, 0]
						}
					}
				},
				"Head": {
					"rotation": {
						"0.0": {
							"vector": [0, 0, 0]
						},
						"1.25": {
							"vector": [0, 0, 0]
						},
						"1.3333": {
							"vector": [0.96539, 1.84223, 55.06341],
							"easing": "easeInOutBack"
						},
						"1.4167": {
							"vector": [0, 0, 0]
						},
						"2.0": {
							"vector": [0, 0, 0]
						}
					},
					"position": {
						"0.0": {
							"vector": [0, 0, 0]
						},
						"1.25": {
							"vector": [0, 0, 0]
						},
						"1.4167": {
							"vector": [0, 0, 0]
						},
						"2.0": {
							"vector": [0, 0, 0]
						}
					}
				},
				"check": {
					"rotation": {
						"0.0": {
							"vector": [0, 0, 0]
						},
						"0.75": {
							"vector": [-20.75399, 2.79371, -2.78474],
							"easing": "linear"
						},
						"1.4167": {
							"vector": [11.24522, 9.24863, 3.03318],
							"easing": "easeInOutSine"
						},
						"2.0": {
							"vector": [0, 0, 0],
							"easing": "linear"
						}
					},
					"position": {
						"0.0": {
							"vector": [0, 0, 0]
						},
						"2.0": {
							"vector": [0, 0, 0]
						}
					}
				},
				"check2": {
					"rotation": {
						"0.0": {
							"vector": [0, 0, 0]
						},
						"0.4583": {
							"vector": [-20.75399, 2.79371, -2.78474],
							"easing": "linear"
						},
						"1.5833": {
							"vector": [11.24522, 9.24863, 3.03318],
							"easing": "easeInOutSine"
						},
						"2.0": {
							"vector": [0, 0, 0],
							"easing": "linear"
						}
					},
					"position": {
						"0.0": {
							"vector": [0, 0, 0]
						},
						"2.0": {
							"vector": [0, 0, 0]
						}
					}
				},
				"bone6": {
					"rotation": {
						"0.0": {
							"vector": [0, 0, 0]
						},
						"1.25": {
							"vector": [5, 0, -6],
							"easing": "easeInOutSine"
						},
						"2.0": {
							"vector": [0, 0, 0],
							"easing": "easeInOutSine"
						}
					},
					"position": {
						"0.0": {
							"vector": [0, 0, 0]
						},
						"2.0": {
							"vector": [0, 0, 0]
						}
					}
				},
				"LeftLeg": {
					"rotation": {
						"vector": [0, 0, 0]
					},
					"position": {
						"vector": [0, 0, 0]
					}
				},
				"bone": {
					"rotation": {
						"0.0": {
							"vector": [0, 0, 0]
						},
						"1.25": {
							"vector": [8, 0, 0],
							"easing": "easeInOutSine"
						},
						"2.0": {
							"vector": [0, 0, 0],
							"easing": "easeInOutSine"
						}
					},
					"position": {
						"0.0": {
							"vector": [0, 0, 0]
						},
						"2.0": {
							"vector": [0, 0, 0]
						}
					}
				},
				"BothArms": {
					"rotation": {
						"0.0": {
							"vector": [-17.5, 0, 0]
						},
						"1.25": {
							"vector": [-28.5, 0, 0],
							"easing": "easeInOutSine"
						},
						"2.0": {
							"vector": [-17.5, 0, 0],
							"easing": "easeInOutSine"
						}
					},
					"position": {
						"0.0": {
							"vector": [0, 0, 0]
						},
						"2.0": {
							"vector": [0, 0, 0]
						}
					}
				}
			}
		},
		"walk": {
			"loop": true,
			"animation_length": 2,
			"bones": {
				"Head": {
					"rotation": {
						"0.0": {
							"vector": [0, 0, 0]
						},
						"1.25": {
							"vector": [0, 0, 0]
						},
						"1.3333": {
							"vector": [0.96539, 1.84223, 55.06341],
							"easing": "easeInOutBack"
						},
						"1.4167": {
							"vector": [0, 0, 0]
						},
						"2.0": {
							"vector": [0, 0, 0]
						}
					},
					"position": {
						"0.0": {
							"vector": [0, 0, 0]
						},
						"1.25": {
							"vector": [0, 0, 0]
						},
						"1.4167": {
							"vector": [0, 0, 0]
						},
						"2.0": {
							"vector": [0, 0, 0]
						}
					}
				},
				"check": {
					"rotation": {
						"0.0": {
							"vector": [0, 0, 0]
						},
						"0.75": {
							"vector": [-20.75399, 2.79371, -2.78474],
							"easing": "linear"
						},
						"1.4167": {
							"vector": [11.24522, 9.24863, 3.03318],
							"easing": "easeInOutSine"
						},
						"2.0": {
							"vector": [0, 0, 0],
							"easing": "linear"
						}
					},
					"position": {
						"0.0": {
							"vector": [0, 0, 0]
						},
						"2.0": {
							"vector": [0, 0, 0]
						}
					}
				},
				"check2": {
					"rotation": {
						"0.0": {
							"vector": [0, 0, 0]
						},
						"0.4583": {
							"vector": [-20.75399, 2.79371, -2.78474],
							"easing": "linear"
						},
						"1.5833": {
							"vector": [11.24522, 9.24863, 3.03318],
							"easing": "easeInOutSine"
						},
						"2.0": {
							"vector": [0, 0, 0],
							"easing": "linear"
						}
					},
					"position": {
						"0.0": {
							"vector": [0, 0, 0]
						},
						"2.0": {
							"vector": [0, 0, 0]
						}
					}
				},
				"LeftLeg": {
					"rotation": {
						"0.0": {
							"vector": [-15, 0, 0]
						},
						"0.5": {
							"vector": [0, 0, 0]
						},
						"1.0": {
							"vector": [18, 0, 0]
						},
						"1.5": {
							"vector": [0, 0, 0]
						},
						"2.0": {
							"vector": [-15, 0, 0]
						}
					},
					"position": {
						"0.0": {
							"vector": [0, 0, 0]
						},
						"0.5": {
							"vector": [0, 0, 0]
						},
						"1.0": {
							"vector": [0, 0, 0]
						},
						"1.5": {
							"vector": [0, 0, 0]
						},
						"2.0": {
							"vector": [0, 0, 0]
						}
					}
				},
				"bone3": {
					"rotation": {
						"0.0": {
							"vector": [-9, 0, 0]
						},
						"0.5": {
							"vector": [0, 0, 0]
						},
						"1.0": {
							"vector": [13, 0, 0]
						},
						"1.5": {
							"vector": [0, 0, 0]
						},
						"2.0": {
							"vector": [-9, 0, 0]
						}
					},
					"position": {
						"0.0": {
							"vector": [0, 0, 0]
						},
						"0.5": {
							"vector": [0, 0, 0]
						},
						"1.5": {
							"vector": [0, 0, 0]
						},
						"2.0": {
							"vector": [0, 0, 0]
						}
					}
				},
				"RightLeg": {
					"rotation": {
						"0.0": {
							"vector": [18, 0, 0]
						},
						"0.5": {
							"vector": [0, 0, 0]
						},
						"1.0": {
							"vector": [-15, 0, 0]
						},
						"1.5": {
							"vector": [0, 0, 0]
						},
						"2.0": {
							"vector": [18, 0, 0]
						}
					},
					"position": {
						"0.0": {
							"vector": [0, 0, 0]
						},
						"0.5": {
							"vector": [0, 0, 0]
						},
						"1.0": {
							"vector": [0, 0, 0]
						},
						"1.5": {
							"vector": [0, 0, 0]
						},
						"2.0": {
							"vector": [0, 0, 0]
						}
					}
				},
				"bone2": {
					"rotation": {
						"0.0": {
							"vector": [13, 0, 0]
						},
						"0.5": {
							"vector": [0, 0, 0]
						},
						"1.0": {
							"vector": [-9, 0, 0]
						},
						"1.5": {
							"vector": [0, 0, 0]
						},
						"2.0": {
							"vector": [13, 0, 0]
						}
					},
					"position": {
						"0.0": {
							"vector": [0, 0, 0]
						},
						"0.5": {
							"vector": [0, 0, 0]
						},
						"1.0": {
							"vector": [0, 0, 0]
						},
						"1.5": {
							"vector": [0, 0, 0]
						},
						"2.0": {
							"vector": [0, 0, 0]
						}
					}
				},
				"UPERBODY": {
					"rotation": {
						"0.0": {
							"vector": [0, 0, 0]
						},
						"1.0": {
							"vector": [3, 0, 0],
							"easing": "easeInOutSine"
						},
						"2.0": {
							"vector": [0, 0, 0],
							"easing": "easeInOutSine"
						}
					},
					"position": {
						"0.0": {
							"vector": [0, 0, 0]
						},
						"2.0": {
							"vector": [0, 0, 0]
						}
					}
				},
				"bone5": {
					"rotation": {
						"0.0": {
							"vector": [0, 0, 0]
						},
						"1.25": {
							"vector": [5, 0, -6],
							"easing": "easeInOutSine"
						},
						"2.0": {
							"vector": [0, 0, 0],
							"easing": "easeInOutSine"
						}
					},
					"position": {
						"0.0": {
							"vector": [0, 0, 0]
						},
						"2.0": {
							"vector": [0, 0, 0]
						}
					}
				},
				"bone6": {
					"rotation": {
						"0.0": {
							"vector": [0, 0, 0]
						},
						"1.25": {
							"vector": [5, 0, -6],
							"easing": "easeInOutSine"
						},
						"2.0": {
							"vector": [0, 0, 0],
							"easing": "easeInOutSine"
						}
					},
					"position": {
						"0.0": {
							"vector": [0, 0, 0]
						},
						"2.0": {
							"vector": [0, 0, 0]
						}
					}
				},
				"bone": {
					"rotation": {
						"0.0": {
							"vector": [0, 0, 0]
						},
						"1.25": {
							"vector": [8, 0, 0],
							"easing": "easeInOutSine"
						},
						"2.0": {
							"vector": [0, 0, 0],
							"easing": "easeInOutSine"
						}
					},
					"position": {
						"0.0": {
							"vector": [0, 0, 0]
						},
						"2.0": {
							"vector": [0, 0, 0]
						}
					}
				},
				"BothArms": {
					"rotation": {
						"0.0": {
							"vector": [0.5, 0, 0]
						},
						"1.0": {
							"vector": [-14.5, 0, 0],
							"easing": "easeInOutSine"
						},
						"2.0": {
							"vector": [0.5, 0, 0]
						}
					},
					"position": {
						"0.0": {
							"vector": [0, 0, 0]
						},
						"2.0": {
							"vector": [0, 0, 0]
						}
					}
				},
				"bone8": {
					"rotation": {
						"0.0": {
							"vector": [21, 0, 0]
						},
						"0.5": {
							"vector": [0, 0, 0]
						},
						"1.0": {
							"vector": [-20, 0, 0]
						},
						"1.5": {
							"vector": [0, 0, 0]
						},
						"2.0": {
							"vector": [21, 0, 0]
						}
					},
					"position": {
						"0.0": {
							"vector": [0, 0, 0]
						},
						"2.0": {
							"vector": [0, 0, 0]
						}
					}
				},
				"bone9": {
					"rotation": {
						"0.0": {
							"vector": [-20, 0, 0]
						},
						"0.5": {
							"vector": [0, 0, 0]
						},
						"1.0": {
							"vector": [21, 0, 0]
						},
						"1.5": {
							"vector": [0, 0, 0]
						},
						"2.0": {
							"vector": [-20, 0, 0]
						}
					}
				}
			}
		},
		"agrwalk": {
			"loop": true,
			"animation_length": 0.75,
			"bones": {
				"Head": {
					"rotation": {
						"0.0": {
							"vector": [0, 0, 0]
						},
						"0.375": {
							"vector": [-3, 0, 0],
							"easing": "easeInOutSine"
						},
						"0.75": {
							"vector": [0, 0, 0]
						}
					},
					"position": {
						"0.0": {
							"vector": [0, 0, 0]
						},
						"0.75": {
							"vector": [0, 0, 0]
						}
					}
				},
				"LeftArm": {
					"rotation": {
						"0.0": {
							"vector": [-15, 0, -20]
						},
						"0.4167": {
							"vector": [-12, 0, -20],
							"easing": "easeInOutSine"
						},
						"0.75": {
							"vector": [-15, 0, -20],
							"easing": "easeInOutSine"
						}
					}
				},
				"LeftLeg": {
					"rotation": {
						"0.0": {
							"vector": [65, 0, 0]
						},
						"0.25": {
							"vector": [-2.5, 0, 0]
						},
						"0.5": {
							"vector": [-70, 0, 0]
						},
						"0.75": {
							"vector": [65, 0, 0]
						}
					}
				},
				"bone3": {
					"rotation": {
						"0.0": {
							"vector": [67.5, 0, 0]
						},
						"0.0833": {
							"vector": [33.33, 0, 0]
						},
						"0.25": {
							"vector": [20, 0, 0]
						},
						"0.4583": {
							"vector": [77.5, 0, 0]
						},
						"0.5833": {
							"vector": [-16.25, 0, 0]
						},
						"0.7083": {
							"vector": [20, 0, 0]
						},
						"0.75": {
							"vector": [67.5, 0, 0]
						}
					}
				},
				"RightLeg": {
					"rotation": {
						"0.0": {
							"vector": [-70, 0, 0]
						},
						"0.25": {
							"vector": [-2.5, 0, 0]
						},
						"0.5": {
							"vector": [65, 0, 0]
						},
						"0.75": {
							"vector": [-70, 0, 0]
						}
					}
				},
				"bone2": {
					"rotation": {
						"0.0": {
							"vector": [77.5, 0, 0]
						},
						"0.125": {
							"vector": [-16.25, 0, 0]
						},
						"0.25": {
							"vector": [20, 0, 0]
						},
						"0.5": {
							"vector": [67.5, 0, 0]
						},
						"0.5833": {
							"vector": [33.33, 0, 0]
						},
						"0.625": {
							"vector": [20, 0, 0]
						},
						"0.75": {
							"vector": [77.5, 0, 0]
						}
					}
				},
				"RightArm": {
					"rotation": {
						"0.0": {
							"vector": [15, 0, 15]
						},
						"0.375": {
							"vector": [9, 0, 15],
							"easing": "easeInOutSine"
						},
						"0.75": {
							"vector": [15, 0, 15],
							"easing": "easeInOutSine"
						}
					},
					"position": {
						"0.0": {
							"vector": [0, 0, 0]
						},
						"0.75": {
							"vector": [0, 0, 0],
							"easing": "easeInOutSine"
						}
					}
				},
				"UPERBODY": {
					"rotation": {
						"0.0": {
							"vector": [12.5, 0, 0]
						},
						"0.375": {
							"vector": [14.5, 0, 0],
							"easing": "easeInOutSine"
						},
						"0.75": {
							"vector": [12.5, 0, 0],
							"easing": "easeInOutSine"
						}
					}
				},
				"bone5": {
					"rotation": {
						"0.0": {
							"vector": [-127.28767, -14.60471, 21.40734]
						},
						"0.75": {
							"vector": [-127.28767, -14.60471, 21.40734]
						}
					},
					"position": {
						"0.0": {
							"vector": [0, 0, -0.5]
						},
						"0.75": {
							"vector": [0, 0, -0.5]
						}
					}
				},
				"bone6": {
					"rotation": {
						"0.0": {
							"vector": [120.4522, 6.06022, 14.5759]
						},
						"0.75": {
							"vector": [120.4522, 6.06022, 14.5759]
						}
					},
					"position": {
						"0.0": {
							"vector": [0, 0, 1.3]
						},
						"0.75": {
							"vector": [0, 0, 1.3]
						}
					}
				}
			}
		},
		"attack": {
			"animation_length": 0.75,
			"bones": {
				"Head": {
					"rotation": {
						"0.0": {
							"vector": [0, 0, 0]
						},
						"0.0833": {
							"vector": [-12.5, 0, 0]
						},
						"0.75": {
							"vector": [0, 0, 0]
						}
					},
					"position": {
						"0.0": {
							"vector": [0, 0, 0]
						},
						"0.75": {
							"vector": [0, 0, 0]
						}
					}
				},
				"check": {
					"rotation": {
						"0.0": {
							"vector": [0, 0, 0]
						},
						"0.0833": {
							"vector": [22.84033, -11.29208, 13.39536]
						},
						"0.75": {
							"vector": [0, 0, 0]
						}
					},
					"position": {
						"0.0": {
							"vector": [0, 0, 0]
						},
						"0.75": {
							"vector": [0, 0, 0]
						}
					}
				},
				"check2": {
					"rotation": {
						"0.0": {
							"vector": [0, 0, 0]
						},
						"0.0833": {
							"vector": [-18.03776, 14.46063, -40.8354]
						},
						"0.75": {
							"vector": [0, 0, 0]
						}
					},
					"position": {
						"0.0": {
							"vector": [0, 0, 0]
						},
						"0.75": {
							"vector": [0, 0, 0]
						}
					}
				},
				"LeftArm": {
					"rotation": {
						"0.0": {
							"vector": [-2.5, 0, -20]
						},
						"0.0833": {
							"vector": [97.21475, -22.42777, -18.16468]
						},
						"0.75": {
							"vector": [-2.5, 0, -20]
						}
					}
				},
				"RightArm": {
					"rotation": {
						"0.0": {
							"vector": [0, 0, 15]
						},
						"0.0833": {
							"vector": [-78.353, -20.56204, 5.67343]
						},
						"0.75": {
							"vector": [0, 0, 15]
						}
					},
					"position": {
						"0.0": {
							"vector": [0, 0, 0]
						},
						"0.0833": {
							"vector": [0, -2.2, 0]
						},
						"0.75": {
							"vector": [0, 0, 0]
						}
					}
				},
				"UPERBODY": {
					"rotation": {
						"0.0": {
							"vector": [0, 0, 0]
						},
						"0.0833": {
							"vector": [13, 0, 0]
						},
						"0.75": {
							"vector": [0, 0, 0]
						}
					},
					"position": {
						"0.0": {
							"vector": [0, 0, 0]
						},
						"0.75": {
							"vector": [0, 0, 0]
						}
					}
				},
				"bone6": {
					"rotation": {
						"0.0": {
							"vector": [110.99692, -18.17696, 39.10406]
						},
						"0.0833": {
							"vector": [12.1251, 31.59643, 9.44156]
						},
						"0.75": {
							"vector": [110.99692, -18.17696, 39.10406]
						}
					}
				},
				"bone5": {
					"rotation": {
						"0.0": {
							"vector": [-106.60179, 11.31335, 33.34411]
						},
						"0.0833": {
							"vector": [-38.67712, -21.20942, 27.05673]
						},
						"0.75": {
							"vector": [-106.60179, 11.31335, 33.34411]
						}
					}
				}
			}
		},
		"attacktwo": {
			"animation_length": 0.5,
			"bones": {
				"bone": {
					"rotation": {
						"0.0": {
							"vector": [0, -27, 0]
						},
						"0.5": {
							"vector": [0, 18, 0],
							"easing": "easeInOutBack"
						}
					}
				},
				"LeftArm": {
					"rotation": {
						"0.0": {
							"vector": [202.25085, -8.67545, 53.98864]
						},
						"0.5": {
							"vector": [83.02274, 1.08556, 51.80789],
							"easing": "easeInOutBack"
						}
					}
				},
				"bone6": {
					"rotation": {
						"0.0": {
							"vector": [103, 0, 0]
						},
						"0.5": {
							"vector": [-4, 0, 0],
							"easing": "easeInOutBack"
						}
					}
				}
			}
		}
	},
	"geckolib_format_version": 2
}